{
  "$schema": "https://developer.microsoft.com/json-schemas/fabric/item/report/definition/visualContainer/2.7.0/schema.json",
  "name": "occ_card",
  "position": {
    "x": 635,
    "y": 80,
    "z": 3,
    "height": 100,
    "width": 195,
    "tabOrder": 3
  },
  "visual": {
    "visualType": "card",
    "query": {
      "queryState": {
        "Values": {
          "projections": [
            {
              "field": {
                "Measure": {
                  "Expression": {
                    "SourceRef": {
                      "Entity": "_Measures"
                    }
                  },
                  "Property": "Occupancy %"
                }
              },
              "queryRef": "_Measures.Occupancy %",
              "nativeQueryRef": "Occupancy %"
            }
          ]
        }
      }
    },
    "drillFilterOtherVisuals": true
  }
}